__init__.py
CV/__init__.py
CV/dataol.py
CV/infer_tool.py
CV/sample_test/__init__.py
CV/sample_test/test.py
aienable-0.0.5.dist-info/LICENSE
aienable-0.0.5.dist-info/METADATA
aienable-0.0.5.dist-info/WHEEL
aienable-0.0.5.dist-info/top_level.txt
aienable-0.0.5.dist-info/RECORD
