Metadata-Version: 2.1
Name: aienable
Version: 0.0.5
Summary: A small pakage for CV
Author-email: linweicheng <linweicheng24@gmail.com>
Project-URL: Homepage, https://github.com/pypa/sampleproject
Project-URL: Bug Tracker, https://github.com/pypa/sampleproject/issues
Classifier: Programming Language :: Python :: 3
Classifier: License :: OSI Approved :: MIT License
Classifier: Operating System :: OS Independent
Requires-Python: >=3.7
License-File: LICENSE
Requires-Dist: lxml ==5.2.1
Requires-Dist: numpy ==1.26.4
Requires-Dist: opencv-python ==4.8.1.78
Requires-Dist: Requests ==2.32.3
